{
  "@context": {
    "estleg": "https://data.riik.ee/ontology/estleg#",
    "owl": "http://www.w3.org/2002/07/owl#",
    "rdf": "http://www.w3.org/1999/02/22-rdf-syntax-ns#",
    "rdfs": "http://www.w3.org/2000/01/rdf-schema#",
    "xsd": "http://www.w3.org/2001/XMLSchema#",
    "dc": "http://purl.org/dc/elements/1.1/",
    "skos": "http://www.w3.org/2004/02/skos/core#",
    "dcterms": "http://purl.org/dc/terms/"
  },
  "@graph": [
    {
      "@id": "estleg:Sanctions_riigihangete_seadus_Map",
      "@type": [
        "owl:Ontology"
      ],
      "rdfs:label": "Sanctions – riigihangete_seadus",
      "dc:source": "riigihangete_seadus"
    },
    {
      "@id": "estleg:Sanction_Riigihangete_seadus_Par_111_fine",
      "@type": [
        "owl:NamedIndividual",
        "estleg:Sanction"
      ],
      "estleg:sanctionType": "fine",
      "estleg:applicableProvision": {
        "@id": "estleg:Riigihangete_seadus_Par_111"
      },
      "estleg:maxPenalty": "100 fine units",
      "rdfs:label": "Fine, max 100 fine units (Riigihangete § § 111.)"
    },
    {
      "@id": "estleg:Sanction_Riigihangete_seadus_Par_112_fine",
      "@type": [
        "owl:NamedIndividual",
        "estleg:Sanction"
      ],
      "estleg:sanctionType": "fine",
      "estleg:applicableProvision": {
        "@id": "estleg:Riigihangete_seadus_Par_112"
      },
      "estleg:maxPenalty": "200 fine units",
      "rdfs:label": "Fine, max 200 fine units (Riigihangete § § 112.)"
    },
    {
      "@id": "estleg:Sanction_Riigihangete_seadus_Par_112_fine_2",
      "@type": [
        "owl:NamedIndividual",
        "estleg:Sanction"
      ],
      "estleg:sanctionType": "fine",
      "estleg:applicableProvision": {
        "@id": "estleg:Riigihangete_seadus_Par_112"
      },
      "estleg:maxPenalty": "2000 EUR",
      "rdfs:label": "Fine, max 2000 EUR (Riigihangete § § 112.)"
    },
    {
      "@id": "estleg:Sanction_Riigihangete_seadus_Par_113_fine",
      "@type": [
        "owl:NamedIndividual",
        "estleg:Sanction"
      ],
      "estleg:sanctionType": "fine",
      "estleg:applicableProvision": {
        "@id": "estleg:Riigihangete_seadus_Par_113"
      },
      "estleg:maxPenalty": "200 fine units",
      "rdfs:label": "Fine, max 200 fine units (Riigihangete § § 113.)"
    },
    {
      "@id": "estleg:Sanction_Riigihangete_seadus_Par_113_fine_2",
      "@type": [
        "owl:NamedIndividual",
        "estleg:Sanction"
      ],
      "estleg:sanctionType": "fine",
      "estleg:applicableProvision": {
        "@id": "estleg:Riigihangete_seadus_Par_113"
      },
      "estleg:maxPenalty": "2000 EUR",
      "rdfs:label": "Fine, max 2000 EUR (Riigihangete § § 113.)"
    }
  ]
}
