{
  "@context": {
    "estleg": "https://data.riik.ee/ontology/estleg#",
    "owl": "http://www.w3.org/2002/07/owl#",
    "rdf": "http://www.w3.org/1999/02/22-rdf-syntax-ns#",
    "rdfs": "http://www.w3.org/2000/01/rdf-schema#",
    "xsd": "http://www.w3.org/2001/XMLSchema#",
    "dc": "http://purl.org/dc/elements/1.1/",
    "skos": "http://www.w3.org/2004/02/skos/core#",
    "dcterms": "http://purl.org/dc/terms/"
  },
  "@graph": [
    {
      "@id": "estleg:AKEKR_Map_2026",
      "@type": [
        "owl:Ontology"
      ],
      "rdfs:label": "Arheoloogiapärandi kaitse Euroopa konventsiooni ratifitseerimise seadus teemakaardistus",
      "dc:source": "Arheoloogiapärandi kaitse Euroopa konventsiooni ratifitseerimise seadus",
      "estleg:entryIntoForce": {
        "@value": "2002-06-01",
        "@type": "xsd:date"
      },
      "estleg:temporalStatus": "inForce",
      "estleg:affectedBy": [
        {
          "@id": "estleg:Draft_JDM26_0168"
        },
        {
          "@id": "estleg:Draft_JDM24_1337"
        },
        {
          "@id": "estleg:Draft_SOM24_0739"
        },
        {
          "@id": "estleg:Draft_RAM24_0675"
        },
        {
          "@id": "estleg:Draft_SOM22_0462"
        },
        {
          "@id": "estleg:Draft_RAM21_1017"
        },
        {
          "@id": "estleg:Draft_KLIM20_0769"
        },
        {
          "@id": "estleg:Draft_KLIM17_1384"
        },
        {
          "@id": "estleg:Draft_VM17_0312"
        },
        {
          "@id": "estleg:Draft_JDM17_0367"
        },
        {
          "@id": "estleg:Draft_VM16_1229"
        },
        {
          "@id": "estleg:Draft_KLIM15_0496"
        },
        {
          "@id": "estleg:Draft_VM14_1375"
        },
        {
          "@id": "estleg:Draft_MKM14_0010"
        },
        {
          "@id": "estleg:Draft_VM13_1628"
        },
        {
          "@id": "estleg:Draft_SOM11_0845"
        },
        {
          "@id": "estleg:Draft_SOM11_0897"
        },
        {
          "@id": "estleg:Draft_RAM11_0654"
        },
        {
          "@id": "estleg:Draft_SOM11_0611"
        },
        {
          "@id": "estleg:Draft_VM21_0305"
        },
        {
          "@id": "estleg:Draft_KLIM18_0273"
        },
        {
          "@id": "estleg:Draft_VM15_1467"
        },
        {
          "@id": "estleg:Draft_VM14_0907"
        }
      ],
      "dcterms:subject": [
        {
          "@id": "http://eurovoc.europa.eu/0411"
        },
        {
          "@id": "http://eurovoc.europa.eu/2446"
        }
      ]
    },
    {
      "@id": "estleg:LegalProvision_AKEKR",
      "@type": [
        "owl:Class"
      ],
      "rdfs:label": "Õigusnorm (paragrahv)",
      "rdfs:subClassOf": {
        "@id": "estleg:LegalProvision"
      }
    },
    {
      "@id": "estleg:AKEKR_Par_1",
      "@type": [
        "owl:NamedIndividual",
        "estleg:LegalProvision_AKEKR"
      ],
      "estleg:paragrahv": "§ 1.",
      "rdfs:label": "§ 1.",
      "estleg:sourceAct": "Arheoloogiapärandi kaitse Euroopa konventsiooni ratifitseerimise seadus",
      "estleg:summary": "Ratifitseerida juurdelisatud arheoloogiapärandi kaitse Euroopa konventsioon./13089481, mis on sõlmitud 1992. aasta 16. jaanuaril Vallettas ja alla kirjutatud Eesti Vabariigi poolt 1996. aasta 3. mail Strasbourg'is.<table border=\"0\" width=\"85%\"> <tbody><tr> <td width=\"50%\"> </td> <td width=\"50%\"> <div align=\"right\"> <strong>Riigikogu esimees Toomas SAVI</strong> </div> </td> </tr> </tbody></table><p> Õiend<a name=\"o\"> </a><br/>Lisatud andmed väljakuulutamise kohta. </p> Ratifitseerida juurdelisat",
      "estleg:competentAuthority": [
        {
          "@id": "estleg:Institution_riigikogu"
        }
      ],
      "estleg:competenceType": "general",
      "estleg:semanticallySimilarTo": [
        {
          "@id": "estleg:EAKKR_Par_1"
        },
        {
          "@id": "estleg:UKKKR_Par_2"
        },
        {
          "@id": "estleg:UNAUKPAK1961_Par_2"
        },
        {
          "@id": "estleg:PEVAKVKTEKSP_Par_4"
        },
        {
          "@id": "estleg:UPKLR_5_Par_4"
        }
      ]
    }
  ]
}
