{
  "@context": {
    "estleg": "https://data.riik.ee/ontology/estleg#",
    "owl": "http://www.w3.org/2002/07/owl#",
    "rdf": "http://www.w3.org/1999/02/22-rdf-syntax-ns#",
    "rdfs": "http://www.w3.org/2000/01/rdf-schema#",
    "xsd": "http://www.w3.org/2001/XMLSchema#",
    "dc": "http://purl.org/dc/elements/1.1/",
    "skos": "http://www.w3.org/2004/02/skos/core#",
    "dcterms": "http://purl.org/dc/terms/"
  },
  "@graph": [
    {
      "@id": "estleg:RVastS_Map_2026",
      "@type": [
        "owl:Ontology"
      ],
      "rdfs:label": "Riigivastutuse seadus teemakaardistus",
      "dc:source": "Riigivastutuse seadus",
      "estleg:entryIntoForce": {
        "@value": "2002-01-01",
        "@type": "xsd:date"
      },
      "estleg:repealDate": {
        "@value": "2006-11-17",
        "@type": "xsd:date"
      },
      "estleg:lastAmendmentDate": {
        "@value": "2004-06-28",
        "@type": "xsd:date"
      },
      "estleg:publicationDate": {
        "@value": "2001-01-01",
        "@type": "xsd:date"
      },
      "estleg:temporalStatus": "repealed",
      "estleg:amendedBy": [
        {
          "@id": "estleg:Amendment_riigivastutuse_seadus_1"
        },
        {
          "@id": "estleg:Amendment_riigivastutuse_seadus_2"
        },
        {
          "@id": "estleg:Amendment_riigivastutuse_seadus_3"
        },
        {
          "@id": "estleg:Amendment_riigivastutuse_seadus_4"
        },
        {
          "@id": "estleg:Amendment_riigivastutuse_seadus_5"
        },
        {
          "@id": "estleg:Amendment_riigivastutuse_seadus_6"
        },
        {
          "@id": "estleg:Amendment_riigivastutuse_seadus_7"
        },
        {
          "@id": "estleg:Amendment_riigivastutuse_seadus_8"
        },
        {
          "@id": "estleg:Amendment_riigivastutuse_seadus_9"
        },
        {
          "@id": "estleg:Amendment_riigivastutuse_seadus_10"
        },
        {
          "@id": "estleg:Amendment_riigivastutuse_seadus_11"
        },
        {
          "@id": "estleg:Amendment_riigivastutuse_seadus_12"
        },
        {
          "@id": "estleg:Amendment_riigivastutuse_seadus_13"
        },
        {
          "@id": "estleg:Amendment_riigivastutuse_seadus_14"
        },
        {
          "@id": "estleg:Amendment_riigivastutuse_seadus_15"
        },
        {
          "@id": "estleg:Amendment_riigivastutuse_seadus_16"
        },
        {
          "@id": "estleg:Amendment_riigivastutuse_seadus_17"
        },
        {
          "@id": "estleg:Amendment_riigivastutuse_seadus_18"
        },
        {
          "@id": "estleg:Amendment_riigivastutuse_seadus_19"
        }
      ],
      "dcterms:subject": [
        {
          "@id": "http://eurovoc.europa.eu/2441"
        },
        {
          "@id": "http://eurovoc.europa.eu/2431"
        },
        {
          "@id": "http://eurovoc.europa.eu/3611"
        },
        {
          "@id": "http://eurovoc.europa.eu/1221"
        },
        {
          "@id": "http://eurovoc.europa.eu/2416"
        }
      ]
    },
    {
      "@id": "estleg:LegalProvision_riigivastutuse_seadus",
      "@type": [
        "owl:Class"
      ],
      "rdfs:label": "Õigusnorm (paragrahv)",
      "rdfs:subClassOf": {
        "@id": "estleg:LegalProvision"
      }
    },
    {
      "@id": "estleg:Cluster_RVastS_1",
      "@type": [
        "owl:NamedIndividual",
        "estleg:TopicCluster"
      ],
      "rdfs:label": "§1–2 ÜLDSÄTTED"
    },
    {
      "@id": "estleg:Cluster_RVastS_2",
      "@type": [
        "owl:NamedIndividual",
        "estleg:TopicCluster"
      ],
      "rdfs:label": "§3–6 NÕUDED HALDUSAKTI VÕI TOIMINGU SUHTES"
    },
    {
      "@id": "estleg:Cluster_RVastS_3",
      "@type": [
        "owl:NamedIndividual",
        "estleg:TopicCluster"
      ],
      "rdfs:label": "§7–21 KAHJU HÜVITAMINE"
    },
    {
      "@id": "estleg:Cluster_RVastS_4",
      "@type": [
        "owl:NamedIndividual",
        "estleg:TopicCluster"
      ],
      "rdfs:label": "§22–24 ALUSETU RIKASTUMINE"
    },
    {
      "@id": "estleg:Cluster_RVastS_5",
      "@type": [
        "owl:NamedIndividual",
        "estleg:TopicCluster"
      ],
      "rdfs:label": "LÕPPSÄTTED"
    },
    {
      "@id": "estleg:RVastS_Par_1",
      "@type": [
        "owl:NamedIndividual",
        "estleg:LegalProvision_riigivastutuse_seadus"
      ],
      "estleg:paragrahv": "§ 1.",
      "rdfs:label": "§ 1. Seaduse reguleerimisala",
      "estleg:sourceAct": "Riigivastutuse seadus",
      "estleg:summary": "1 (1) Käesolev seadus sätestab avaliku võimu volituste rakendamisel ja muude avalike ülesannete täitmisel rikutud õiguste kaitse ja taastamise ning tekitatud kahju hüvitamise alused ja korra (riigivastutus). Käesolev seadus sätestab avaliku võimu volituste rakendamisel ja muude avalike ülesannete täitmisel rikutud õiguste kaitse ja taastamise ning tekitatud kahju hüvitamise alused ja korra (riigivastutus). 2 (2) Käesolev seadus ei reguleeri õiguste taastamist ega kahju hüvitamist eraõiguslikus s",
      "estleg:requestedCluster": "estleg:Cluster_RVastS_1"
    },
    {
      "@id": "estleg:RVastS_Par_2",
      "@type": [
        "owl:NamedIndividual",
        "estleg:LegalProvision_riigivastutuse_seadus"
      ],
      "estleg:paragrahv": "§ 2.",
      "rdfs:label": "§ 2. Õiguste kaitse ja taastamise ning kahju hüvitamise nõuded",
      "estleg:sourceAct": "Riigivastutuse seadus",
      "estleg:summary": "1 (1) Käesoleva seaduse alusel võib isik riigilt, kohaliku omavalitsuse üksuselt, muult avalik-õiguslikult juriidiliselt isikult või muult avalikke ülesandeid avalik-õiguslikul alusel väljaspool alluvussuhet teostavalt isikult (avaliku võimu kandjalt) nõuda: 1 1) haldusakti kehtetuks tunnistamist; RT I 2004 56 405 778951 2004-07-25+03:00 2 2) jätkuva toimingu lõpetamist; 3 3) haldusakti andmisest või toimingu sooritamisest hoidumist; 4 4) haldusakti andmist või toimingu sooritamist; 5 5) tekitat",
      "estleg:requestedCluster": "estleg:Cluster_RVastS_1",
      "estleg:normativeType": [
        {
          "@id": "estleg:NormType_Right"
        }
      ],
      "estleg:competentAuthority": [
        {
          "@id": "estleg:Institution_kohalik_omavalitsus"
        }
      ],
      "estleg:competenceType": "general"
    },
    {
      "@id": "estleg:RVastS_Par_3",
      "@type": [
        "owl:NamedIndividual",
        "estleg:LegalProvision_riigivastutuse_seadus"
      ],
      "estleg:paragrahv": "§ 3.",
      "rdfs:label": "§ 3. Haldusakti kehtetuks tunnistamise nõue",
      "estleg:sourceAct": "Riigivastutuse seadus",
      "estleg:summary": "1 (1) Isik võib nõuda haldusakti kehtetuks tunnistamist üksnes selles ulatuses, milles rikutakse tema õigusi, kui seadusega ei ole sätestatud teisiti. Isik võib nõuda haldusakti kehtetuks tunnistamist üksnes selles ulatuses, milles rikutakse tema õigusi, kui seadusega ei ole sätestatud teisiti. 2 (2) Haldusakti ei tunnistata kehtetuks, kui isiku õigused on taastatud haldusakti muutmisega. Haldusakti ei tunnistata kehtetuks, kui isiku õigused on taastatud haldusakti muutmisega. 3 (3) Haldusakti v",
      "estleg:requestedCluster": "estleg:Cluster_RVastS_2",
      "estleg:normativeType": [
        {
          "@id": "estleg:NormType_Right"
        }
      ],
      "estleg:referencedBy": [
        {
          "@id": "estleg:RVastS_Par_7"
        }
      ]
    },
    {
      "@id": "estleg:RVastS_Par_4",
      "@type": [
        "owl:NamedIndividual",
        "estleg:LegalProvision_riigivastutuse_seadus"
      ],
      "estleg:paragrahv": "§ 4.",
      "rdfs:label": "§ 4. Toimingu lõpetamise nõue",
      "estleg:sourceAct": "Riigivastutuse seadus",
      "estleg:summary": "1 (1) Isik võib nõuda halduse jätkuva toiminguga kaasneva õiguste rikkumise lõpetamist, kui see on võimalik ülemääraste kuludeta. Õiguste rikkumise lõpetamise kulud on ülemäärased, kui need ületavad oluliselt isikule õiguste rikkumisega tekitatavat kahju. Isik võib nõuda halduse jätkuva toiminguga kaasneva õiguste rikkumise lõpetamist, kui see on võimalik ülemääraste kuludeta. Õiguste rikkumise lõpetamise kulud on ülemäärased, kui need ületavad oluliselt isikule õiguste rikkumisega tekitatavat k",
      "estleg:requestedCluster": "estleg:Cluster_RVastS_2",
      "estleg:normativeType": [
        {
          "@id": "estleg:NormType_Right"
        }
      ]
    },
    {
      "@id": "estleg:RVastS_Par_5",
      "@type": [
        "owl:NamedIndividual",
        "estleg:LegalProvision_riigivastutuse_seadus"
      ],
      "estleg:paragrahv": "§ 5.",
      "rdfs:label": "§ 5. Haldusaktist või toimingust hoidumise nõue",
      "estleg:sourceAct": "Riigivastutuse seadus",
      "estleg:summary": "1 (1) Isik võib nõuda haldusakti andmata jätmist või halduse toimingu sooritamata jätmist, kui haldusakt või toiming rikuks tema õigusi ja tooks tõenäoliselt endaga kaasa tagajärje, mida ei saaks kõrvaldada haldusakti või toimingu hilisemal vaidlustamisel. Isik võib nõuda haldusakti andmata jätmist või halduse toimingu sooritamata jätmist, kui haldusakt või toiming rikuks tema õigusi ja tooks tõenäoliselt endaga kaasa tagajärje, mida ei saaks kõrvaldada haldusakti või toimingu hilisemal vaidlust",
      "estleg:requestedCluster": "estleg:Cluster_RVastS_2",
      "estleg:normativeType": [
        {
          "@id": "estleg:NormType_Right"
        }
      ]
    },
    {
      "@id": "estleg:RVastS_Par_6",
      "@type": [
        "owl:NamedIndividual",
        "estleg:LegalProvision_riigivastutuse_seadus"
      ],
      "estleg:paragrahv": "§ 6.",
      "rdfs:label": "§ 6. Haldusakti andmise või toimingu sooritamise nõue",
      "estleg:sourceAct": "Riigivastutuse seadus",
      "estleg:summary": "1 (1) Isik võib nõuda haldusakti andmist või toimingu sooritamist, kui avaliku võimu kandja on kohustatud haldusakti andma või toimingu sooritama ja see puudutab isiku õigusi. Isik võib nõuda haldusakti andmist või toimingu sooritamist, kui avaliku võimu kandja on kohustatud haldusakti andma või toimingu sooritama ja see puudutab isiku õigusi. 2 (2) Kehtetu - RT I 2004 56 405 778951 2004-07-25+03:00 Kehtetu - 3 (3) Taotlus haldusakti andmiseks või toimingu sooritamiseks tuleb esitada selleks päd",
      "estleg:requestedCluster": "estleg:Cluster_RVastS_2",
      "estleg:normativeType": [
        {
          "@id": "estleg:NormType_Obligation"
        }
      ]
    },
    {
      "@id": "estleg:RVastS_Par_7",
      "@type": [
        "owl:NamedIndividual",
        "estleg:LegalProvision_riigivastutuse_seadus"
      ],
      "estleg:paragrahv": "§ 7.",
      "rdfs:label": "§ 7. Vastutuse alused",
      "estleg:sourceAct": "Riigivastutuse seadus",
      "estleg:summary": "1 (1) Isik, kelle õigusi on avaliku võimu kandja õigusvastase tegevusega avalik-õiguslikus suhtes rikkunud (edaspidi kannatanu ), võib nõuda talle tekitatud kahju hüvitamist, kui kahju ei olnud võimalik vältida ega ole võimalik kõrvaldada käesoleva seaduse §-des 3, 4 ja 6 sätestatud viisil õiguste kaitsmise või taastamisega. Isik, kelle õigusi on avaliku võimu kandja õigusvastase tegevusega avalik-õiguslikus suhtes rikkunud (edaspidi kannatanu ), võib nõuda talle tekitatud kahju hüvitamist, kui ",
      "estleg:requestedCluster": "estleg:Cluster_RVastS_3",
      "estleg:references": [
        {
          "@id": "estleg:RVastS_Par_3"
        }
      ],
      "estleg:normativeType": [
        {
          "@id": "estleg:NormType_Right"
        }
      ]
    },
    {
      "@id": "estleg:RVastS_Par_8",
      "@type": [
        "owl:NamedIndividual",
        "estleg:LegalProvision_riigivastutuse_seadus"
      ],
      "estleg:paragrahv": "§ 8.",
      "rdfs:label": "§ 8. Varalise kahju hüvitamine",
      "estleg:sourceAct": "Riigivastutuse seadus",
      "estleg:summary": "1 (1) Varaline kahju hüvitatakse rahas. Hüvitisega tuleb luua varaline olukord, milles kannatanu oleks siis, kui tema õigusi ei oleks rikutud. Varaline kahju hüvitatakse rahas. Hüvitisega tuleb luua varaline olukord, milles kannatanu oleks siis, kui tema õigusi ei oleks rikutud. 2 (2) Kehavigastuse tekitamisel või tervise kahjustamisel võib kannatanu nõuda sellega tekitatud kulutuste hüvitamist. Sealhulgas võib kannatanu nõuda järgmiste kulutuste hüvitamist: 1 1) vajalikud ravikulud; 2 2) vajadu",
      "estleg:requestedCluster": "estleg:Cluster_RVastS_3",
      "estleg:normativeType": [
        {
          "@id": "estleg:NormType_Obligation"
        }
      ],
      "estleg:dutyHolder": "Hüvitisega",
      "estleg:referencedBy": [
        {
          "@id": "estleg:RVastS_Par_10"
        }
      ]
    },
    {
      "@id": "estleg:RVastS_Par_9",
      "@type": [
        "owl:NamedIndividual",
        "estleg:LegalProvision_riigivastutuse_seadus"
      ],
      "estleg:paragrahv": "§ 9.",
      "rdfs:label": "§ 9. Mittevaralise kahju hüvitamine",
      "estleg:sourceAct": "Riigivastutuse seadus",
      "estleg:summary": "1 (1) Füüsiline isik võib nõuda mittevaralise kahju rahalist hüvitamist süüliselt väärikuse alandamise, tervise kahjustamise, vabaduse võtmise, kodu või eraelu puutumatuse või sõnumi saladuse rikkumise, au või hea nime teotamise korral. Füüsiline isik võib nõuda mittevaralise kahju rahalist hüvitamist süüliselt väärikuse alandamise, tervise kahjustamise, vabaduse võtmise, kodu või eraelu puutumatuse või sõnumi saladuse rikkumise, au või hea nime teotamise korral. 2 (2) Mittevaraline kahju hüvita",
      "estleg:requestedCluster": "estleg:Cluster_RVastS_3",
      "estleg:normativeType": [
        {
          "@id": "estleg:NormType_Right"
        }
      ]
    },
    {
      "@id": "estleg:RVastS_Par_10",
      "@type": [
        "owl:NamedIndividual",
        "estleg:LegalProvision_riigivastutuse_seadus"
      ],
      "estleg:paragrahv": "§ 10.",
      "rdfs:label": "§ 10. Kahju hüvitamine kolmandatele isikutele",
      "estleg:sourceAct": "Riigivastutuse seadus",
      "estleg:summary": "1 (1) Surma põhjustamisel, kehavigastuse tekitamisel või tervise kahjustamisel on kolmandal isikul õigus nõuda sellega seoses kantud kulutuste, äralangenud ülalpidamise ja mittevaralise kahju hüvitamist eraõiguses sätestatud alustel. Surma põhjustamisel, kehavigastuse tekitamisel või tervise kahjustamisel on kolmandal isikul õigus nõuda sellega seoses kantud kulutuste, äralangenud ülalpidamise ja mittevaralise kahju hüvitamist eraõiguses sätestatud alustel. 2 (2) Äralangenud ülalpidamise hüvitam",
      "estleg:requestedCluster": "estleg:Cluster_RVastS_3",
      "estleg:references": [
        {
          "@id": "estleg:RVastS_Par_8"
        }
      ]
    },
    {
      "@id": "estleg:RVastS_Par_11",
      "@type": [
        "owl:NamedIndividual",
        "estleg:LegalProvision_riigivastutuse_seadus"
      ],
      "estleg:paragrahv": "§ 11.",
      "rdfs:label": "§ 11. Tagajärgede kõrvaldamine",
      "estleg:sourceAct": "Riigivastutuse seadus",
      "estleg:summary": "1 (1) Kannatanu võib avaliku võimu kandjalt rahalise hüvitise asemel nõuda kehtetuks tunnistatud või vastavas osas muudetud haldusakti või toimingu õigusvastaste tagajärgede kõrvaldamist. RT I 2004 56 405 778951 2004-07-25+03:00 Kannatanu võib avaliku võimu kandjalt rahalise hüvitise asemel nõuda kehtetuks tunnistatud või vastavas osas muudetud haldusakti või toimingu õigusvastaste tagajärgede kõrvaldamist. 2 (2) Avaliku võimu kandja on tagajärgede kõrvaldamisel kohustatud rakendama kõiki õigusp",
      "estleg:requestedCluster": "estleg:Cluster_RVastS_3",
      "estleg:normativeType": [
        {
          "@id": "estleg:NormType_Right"
        }
      ]
    },
    {
      "@id": "estleg:RVastS_Par_12",
      "@type": [
        "owl:NamedIndividual",
        "estleg:LegalProvision_riigivastutuse_seadus"
      ],
      "estleg:paragrahv": "§ 12.",
      "rdfs:label": "§ 12. Kahju hüvitamiseks kohustatud isik",
      "estleg:sourceAct": "Riigivastutuse seadus",
      "estleg:summary": "1 (1) Kahju kannatanud isikule on kahju hüvitama kohustatud avaliku võimu kandja, kelle tegevusega kahju tekitati. Tegevusetusega tekitatud kahju on kohustatud hüvitama avaliku võimu kandja, kes jättis õigeaegselt haldusakti andmata või toimingu sooritamata. Kahju kannatanud isikule on kahju hüvitama kohustatud avaliku võimu kandja, kelle tegevusega kahju tekitati. Tegevusetusega tekitatud kahju on kohustatud hüvitama avaliku võimu kandja, kes jättis õigeaegselt haldusakti andmata või toimingu s",
      "estleg:requestedCluster": "estleg:Cluster_RVastS_3",
      "estleg:normativeType": [
        {
          "@id": "estleg:NormType_Obligation"
        }
      ],
      "estleg:dutyHolder": "Tegevusetusega tekitatud kahju",
      "estleg:referencedBy": [
        {
          "@id": "estleg:RVastS_Par_17"
        },
        {
          "@id": "estleg:RVastS_Par_19"
        }
      ]
    },
    {
      "@id": "estleg:RVastS_Par_13",
      "@type": [
        "owl:NamedIndividual",
        "estleg:LegalProvision_riigivastutuse_seadus"
      ],
      "estleg:paragrahv": "§ 13.",
      "rdfs:label": "§ 13. Vastutuse piiramine",
      "estleg:sourceAct": "Riigivastutuse seadus",
      "estleg:summary": "1 (1) Hüvitise suuruse määramisel arvestatakse: 1 1) kahju tekkimise ettenägematust; 2 2) objektiivseid takistusi kahju ärahoidmisel; 3 3) õiguste rikkumise raskust; 4 4) eraõiguses sätestatud piiranguid seoses kannatanu osaga kahju tekitamisel; 5 5) muid asjaolusid, millest tulenevalt kahju hüvitamine täies ulatuses oleks ebaõiglane. Hüvitise suuruse määramisel arvestatakse: kahju tekkimise ettenägematust; objektiivseid takistusi kahju ärahoidmisel; õiguste rikkumise raskust; eraõiguses sätesta",
      "estleg:requestedCluster": "estleg:Cluster_RVastS_3",
      "estleg:referencedBy": [
        {
          "@id": "estleg:RVastS_Par_19"
        }
      ]
    },
    {
      "@id": "estleg:RVastS_Par_14",
      "@type": [
        "owl:NamedIndividual",
        "estleg:LegalProvision_riigivastutuse_seadus"
      ],
      "estleg:paragrahv": "§ 14.",
      "rdfs:label": "§ 14. Õigustloova aktiga tekitatud kahju",
      "estleg:sourceAct": "Riigivastutuse seadus",
      "estleg:summary": "1 (1) Isik võib nõuda õigustloova aktiga või selle andmata jätmisega tekitatud kahju hüvitamist üksnes juhul, kui kahju põhjustati avaliku võimu kandja kohustuste olulise rikkumisega, rikutud kohustuse aluseks olev norm on otsekohaldatav ning isik kuulub õigustloova akti või selle andmata jätmise tõttu eriliselt kannatanud isikute rühma. Isik võib nõuda õigustloova aktiga või selle andmata jätmisega tekitatud kahju hüvitamist üksnes juhul, kui kahju põhjustati avaliku võimu kandja kohustuste olu",
      "estleg:requestedCluster": "estleg:Cluster_RVastS_3",
      "estleg:normativeType": [
        {
          "@id": "estleg:NormType_Right"
        }
      ]
    },
    {
      "@id": "estleg:RVastS_Par_15",
      "@type": [
        "owl:NamedIndividual",
        "estleg:LegalProvision_riigivastutuse_seadus"
      ],
      "estleg:paragrahv": "§ 15.",
      "rdfs:label": "§ 15. Õigusemõistmisel tekitatud kahju",
      "estleg:sourceAct": "Riigivastutuse seadus",
      "estleg:summary": "1 (1) Isik võib nõuda kohtumenetluse käigus, sealhulgas kohtulahendiga tekitatud kahju hüvitamist üksnes juhul, kui kohtunik on kohtumenetluse käigus toime pannud kuriteo. Isik võib nõuda kohtumenetluse käigus, sealhulgas kohtulahendiga tekitatud kahju hüvitamist üksnes juhul, kui kohtunik on kohtumenetluse käigus toime pannud kuriteo. 2 (2) Käesoleva paragrahvi lõiget 1 kohaldatakse ka kahju suhtes, mis on tekkinud: 1 1) vaidluse lahendamisel seadusega vaidluste kohtuväliseks lahendamiseks lood",
      "estleg:requestedCluster": "estleg:Cluster_RVastS_3",
      "estleg:normativeType": [
        {
          "@id": "estleg:NormType_Right"
        }
      ]
    },
    {
      "@id": "estleg:RVastS_Par_16",
      "@type": [
        "owl:NamedIndividual",
        "estleg:LegalProvision_riigivastutuse_seadus"
      ],
      "estleg:paragrahv": "§ 16.",
      "rdfs:label": "§ 16. Õiguspärase haldusakti või toiminguga tekitatud kahju",
      "estleg:sourceAct": "Riigivastutuse seadus",
      "estleg:summary": "1 (1) Isik võib nõuda õiguspärase, kuid tema põhiõigusi või -vabadusi erakordselt piirava haldusakti või halduse toiminguga tekitatud varalise kahju hüvitamist õiglases ulatuses. Isik võib nõuda õiguspärase, kuid tema põhiõigusi või -vabadusi erakordselt piirava haldusakti või halduse toiminguga tekitatud varalise kahju hüvitamist õiglases ulatuses. 2 (2) Kui seadus ei sätesta teisiti, ei saa käesoleva paragrahvi lõikes 1 nimetatud hüvitist nõuda ulatuses, milles: 1 1) põhiõiguste või -vabaduste",
      "estleg:requestedCluster": "estleg:Cluster_RVastS_3",
      "estleg:normativeType": [
        {
          "@id": "estleg:NormType_Right"
        }
      ]
    },
    {
      "@id": "estleg:RVastS_Par_17",
      "@type": [
        "owl:NamedIndividual",
        "estleg:LegalProvision_riigivastutuse_seadus"
      ],
      "estleg:paragrahv": "§ 17.",
      "rdfs:label": "§ 17. Taotluse või kaebuse esitamine",
      "estleg:sourceAct": "Riigivastutuse seadus",
      "estleg:summary": "1 (1) Kahju hüvitamiseks võib esitada taotluse kahju tekitanud haldusorganile või kaebuse halduskohtule. Taotlus kohtu poolt tekitatud kahju hüvitamiseks esitatakse Justiitsministeeriumile. Kahju hüvitamiseks võib esitada taotluse kahju tekitanud haldusorganile või kaebuse halduskohtule. Taotlus kohtu poolt tekitatud kahju hüvitamiseks esitatakse Justiitsministeeriumile. 2 (2) Kahju tekitamisel käesoleva seaduse § 12 lõikes 3 sätestatud juhul esitatakse taotlus haldusorganile, kes kahju tekitanu",
      "estleg:requestedCluster": "estleg:Cluster_RVastS_3",
      "estleg:references": [
        {
          "@id": "estleg:RVastS_Par_12"
        }
      ],
      "estleg:normativeType": [
        {
          "@id": "estleg:NormType_Right"
        }
      ],
      "estleg:referencedBy": [
        {
          "@id": "estleg:RVastS_Par_21"
        }
      ]
    },
    {
      "@id": "estleg:RVastS_Par_18",
      "@type": [
        "owl:NamedIndividual",
        "estleg:LegalProvision_riigivastutuse_seadus"
      ],
      "estleg:paragrahv": "§ 18.",
      "rdfs:label": "§ 18. Taotluse läbivaatamine",
      "estleg:sourceAct": "Riigivastutuse seadus",
      "estleg:summary": "1 (1) Haldusorgan peab taotluse lahendama kahe kuu jooksul selle nõuetekohasest esitamisest arvates. Haldusorgan peab taotluse lahendama kahe kuu jooksul selle nõuetekohasest esitamisest arvates. 2 (2) Kui haldusorgan jätab kahju hüvitamise taotluse rahuldamata või tähtaegselt lahendamata või kui kannatanu ei nõustu hüvitise suuruse või viisiga, võib kannatanu 30 päeva jooksul esitada halduskohtule kaebuse hüvitise väljamõistmiseks. Kui haldusorgan jätab kahju hüvitamise taotluse rahuldamata või",
      "estleg:requestedCluster": "estleg:Cluster_RVastS_3",
      "estleg:normativeType": [
        {
          "@id": "estleg:NormType_Obligation"
        }
      ],
      "estleg:dutyHolder": "Haldusorgan"
    },
    {
      "@id": "estleg:RVastS_Par_19",
      "@type": [
        "owl:NamedIndividual",
        "estleg:LegalProvision_riigivastutuse_seadus"
      ],
      "estleg:paragrahv": "§ 19.",
      "rdfs:label": "§ 19. Regressi alused",
      "estleg:sourceAct": "Riigivastutuse seadus",
      "estleg:summary": "1 (1) Käesolevast peatükist tulenevalt kahju hüvitanud avaliku võimu kandja võib esitada regressinõude käesoleva seaduse § 12 lõigetes 2 ja 3 nimetatud isiku vastu, kelle õigusvastase tegevuse tulemusena kahju tekkis, või avaliku võimu kandja vastu, kelle eest solidaarvastutuse alusel kahju hüvitati. Käesolevast peatükist tulenevalt kahju hüvitanud avaliku võimu kandja võib esitada regressinõude käesoleva seaduse § 12 lõigetes 2 ja 3 nimetatud isiku vastu, kelle õigusvastase tegevuse tulemusena ",
      "estleg:requestedCluster": "estleg:Cluster_RVastS_3",
      "estleg:references": [
        {
          "@id": "estleg:RVastS_Par_12"
        },
        {
          "@id": "estleg:RVastS_Par_13"
        }
      ],
      "estleg:normativeType": [
        {
          "@id": "estleg:NormType_Right"
        }
      ]
    },
    {
      "@id": "estleg:RVastS_Par_20",
      "@type": [
        "owl:NamedIndividual",
        "estleg:LegalProvision_riigivastutuse_seadus"
      ],
      "estleg:paragrahv": "§ 20.",
      "rdfs:label": "§ 20. Hüvitise nõudmise kord",
      "estleg:sourceAct": "Riigivastutuse seadus",
      "estleg:summary": "1 (1) Regressinõude alusel hüvitise saamiseks teeb avaliku võimu kandja isikule kirjaliku ettepaneku, näidates ära kahju hüvitamise ulatuse, korra ja tähtaja ning hüvitise nõudmise aluseks olevad asjaolud. Isik vastab ettepanekule kirjalikult. Regressinõude alusel hüvitise saamiseks teeb avaliku võimu kandja isikule kirjaliku ettepaneku, näidates ära kahju hüvitamise ulatuse, korra ja tähtaja ning hüvitise nõudmise aluseks olevad asjaolud. Isik vastab ettepanekule kirjalikult. 2 (2) Ettepaneku v",
      "estleg:requestedCluster": "estleg:Cluster_RVastS_3"
    },
    {
      "@id": "estleg:RVastS_Par_21",
      "@type": [
        "owl:NamedIndividual",
        "estleg:LegalProvision_riigivastutuse_seadus"
      ],
      "estleg:paragrahv": "§ 21.",
      "rdfs:label": "§ 21. Regressi erijuhud",
      "estleg:sourceAct": "Riigivastutuse seadus",
      "estleg:summary": "1 (1) Ametnik vastutab avaliku võimu kandja ees avaliku teenistuse seaduses (RT I 1995, 16, 228; 1999, 7, 112; 10, 155; 16, 271 ja 276; 2000, 25, 144 ja 145; 28, 167; 102, 672; 2001, 7, 17 ja 18; 17, 78; 42, 233) sätestatud alustel ja korras. Ametnik vastutab avaliku võimu kandja ees avaliku teenistuse seaduses (RT I 1995, 16, 228; 1999, 7, 112; 10, 155; 16, 271 ja 276; 2000, 25, 144 ja 145; 28, 167; 102, 672; 2001, 7, 17 ja 18; 17, 78; 42, 233) sätestatud alustel ja korras. 2 (2) Isik, kes teki",
      "estleg:requestedCluster": "estleg:Cluster_RVastS_3",
      "estleg:references": [
        {
          "@id": "estleg:RVastS_Par_17"
        }
      ]
    },
    {
      "@id": "estleg:RVastS_Par_22",
      "@type": [
        "owl:NamedIndividual",
        "estleg:LegalProvision_riigivastutuse_seadus"
      ],
      "estleg:paragrahv": "§ 22.",
      "rdfs:label": "§ 22. Alusetu rikastumine avalik-õiguslikus suhtes",
      "estleg:sourceAct": "Riigivastutuse seadus",
      "estleg:summary": "1 (1) Isik võib avaliku võimu kandjalt nõuda õigusliku aluseta avalik-õiguslikus suhtes üleantud asja või raha tagastamist, kui seadus ei sätesta teisiti. Kui alusetult saadud asja tagastamine on võimatu või seotud ülemääraste kuludega, võib õigustatud isik nõuda asja väärtuse hüvitamist rahas. Isik võib avaliku võimu kandjalt nõuda õigusliku aluseta avalik-õiguslikus suhtes üleantud asja või raha tagastamist, kui seadus ei sätesta teisiti. Kui alusetult saadud asja tagastamine on võimatu või se",
      "estleg:requestedCluster": "estleg:Cluster_RVastS_4",
      "estleg:normativeType": [
        {
          "@id": "estleg:NormType_Right"
        }
      ],
      "estleg:referencedBy": [
        {
          "@id": "estleg:RVastS_Par_23"
        }
      ]
    },
    {
      "@id": "estleg:RVastS_Par_23",
      "@type": [
        "owl:NamedIndividual",
        "estleg:LegalProvision_riigivastutuse_seadus"
      ],
      "estleg:paragrahv": "§ 23.",
      "rdfs:label": "§ 23. Intress ja asjast saadud kasu",
      "estleg:sourceAct": "Riigivastutuse seadus",
      "estleg:summary": "Lisaks käesoleva seaduse § 22 lõikes 1 sätestatule võib isik nõuda avaliku võimu kandjalt: 1 1) intressi alusetult saadud raha eest kuus protsenti aastas; 2 2) asja võõrandamisest ja asja kasutamisest saadud kasu üleandmist. Lisaks käesoleva seaduse § 22 lõikes 1 sätestatule võib isik nõuda avaliku võimu kandjalt: intressi alusetult saadud raha eest kuus protsenti aastas; asja võõrandamisest ja asja kasutamisest saadud kasu üleandmist.",
      "estleg:requestedCluster": "estleg:Cluster_RVastS_4",
      "estleg:references": [
        {
          "@id": "estleg:RVastS_Par_22"
        }
      ],
      "estleg:normativeType": [
        {
          "@id": "estleg:NormType_Right"
        }
      ]
    },
    {
      "@id": "estleg:RVastS_Par_24",
      "@type": [
        "owl:NamedIndividual",
        "estleg:LegalProvision_riigivastutuse_seadus"
      ],
      "estleg:paragrahv": "§ 24.",
      "rdfs:label": "§ 24. Nõude üle otsustamine",
      "estleg:sourceAct": "Riigivastutuse seadus",
      "estleg:summary": "1 (1) Avalik-õiguslikus suhtes alusetust rikastumisest tuleneva nõude üle otsustab asja või raha saanud haldusorgan haldusaktiga. Haldusaktis märgitakse ära tagastamise või hüvitamise viis ja ulatus. Avaliku võimu kandja omandis oleva kinnisasja või muu registrisse kantud asja tagastamisel õigustatud isikule tehakse omandiõiguse ülemineku kohta kinnistusraamatusse või muusse registrisse kanne haldusakti ja avaliku võimu kandja notariaalselt tõestatud avalduse alusel. Avalik-õiguslikus suhtes alu",
      "estleg:requestedCluster": "estleg:Cluster_RVastS_4"
    },
    {
      "@id": "estleg:RVastS_Par_31",
      "@type": [
        "owl:NamedIndividual",
        "estleg:LegalProvision_riigivastutuse_seadus"
      ],
      "estleg:paragrahv": "§ 31.",
      "rdfs:label": "§ 31. Seaduse rakendamine",
      "estleg:sourceAct": "Riigivastutuse seadus",
      "estleg:summary": "1 (1) Avalik-õiguslikus suhtes tekitatud kahju hüvitamiseks või alusetult saadud raha või asja tagastamiseks enne käesoleva seaduse jõustumist esitatud kaebuse või hagi läbivaatamisel kohaldatakse enne käesoleva seaduse jõustumist kehtinud sätteid ja kahju hüvitamise üldisi põhimõtteid. Avalik-õiguslikus suhtes tekitatud kahju hüvitamiseks või alusetult saadud raha või asja tagastamiseks enne käesoleva seaduse jõustumist esitatud kaebuse või hagi läbivaatamisel kohaldatakse enne käesoleva seadus"
    },
    {
      "@id": "estleg:RVastS_Par_32",
      "@type": [
        "owl:NamedIndividual",
        "estleg:LegalProvision_riigivastutuse_seadus"
      ],
      "estleg:paragrahv": "§ 32.",
      "rdfs:label": "§ 32. Seaduse jõustumine",
      "estleg:sourceAct": "Riigivastutuse seadus",
      "estleg:summary": "Käesolev seadus jõustub 2002. aasta 1. jaanuaril. Käesolev seadus jõustub 2002. aasta 1. jaanuaril."
    }
  ]
}
