{
  "@context": {
    "estleg": "https://data.riik.ee/ontology/estleg#",
    "owl": "http://www.w3.org/2002/07/owl#",
    "rdf": "http://www.w3.org/1999/02/22-rdf-syntax-ns#",
    "rdfs": "http://www.w3.org/2000/01/rdf-schema#",
    "xsd": "http://www.w3.org/2001/XMLSchema#",
    "dc": "http://purl.org/dc/elements/1.1/",
    "skos": "http://www.w3.org/2004/02/skos/core#",
    "dcterms": "http://purl.org/dc/terms/"
  },
  "@graph": [
    {
      "@id": "estleg:VALISS_Map_2026",
      "@type": [
        "owl:Ontology"
      ],
      "rdfs:label": "Välissuhtlemisseadus teemakaardistus",
      "dc:source": "Välissuhtlemisseadus",
      "estleg:entryIntoForce": {
        "@value": "2007-01-01",
        "@type": "xsd:date"
      },
      "estleg:lastAmendmentDate": {
        "@value": "2010-04-22",
        "@type": "xsd:date"
      },
      "estleg:publicationDate": {
        "@value": "2006-01-01",
        "@type": "xsd:date"
      },
      "estleg:temporalStatus": "inForce",
      "estleg:amendedBy": [
        {
          "@id": "estleg:Amendment_valissuhtlemisseadus_1"
        },
        {
          "@id": "estleg:Amendment_valissuhtlemisseadus_2"
        },
        {
          "@id": "estleg:Amendment_valissuhtlemisseadus_3"
        },
        {
          "@id": "estleg:Amendment_valissuhtlemisseadus_4"
        },
        {
          "@id": "estleg:Amendment_valissuhtlemisseadus_5"
        },
        {
          "@id": "estleg:Amendment_valissuhtlemisseadus_6"
        },
        {
          "@id": "estleg:Amendment_valissuhtlemisseadus_7"
        },
        {
          "@id": "estleg:Amendment_valissuhtlemisseadus_8"
        },
        {
          "@id": "estleg:Amendment_valissuhtlemisseadus_9"
        }
      ],
      "dcterms:subject": [
        {
          "@id": "http://eurovoc.europa.eu/2431"
        },
        {
          "@id": "http://eurovoc.europa.eu/0411"
        },
        {
          "@id": "http://eurovoc.europa.eu/2446"
        },
        {
          "@id": "http://eurovoc.europa.eu/1221"
        },
        {
          "@id": "http://eurovoc.europa.eu/5636"
        }
      ]
    },
    {
      "@id": "estleg:LegalProvision_VALISS",
      "@type": [
        "owl:Class"
      ],
      "rdfs:label": "Õigusnorm (paragrahv)",
      "rdfs:subClassOf": {
        "@id": "estleg:LegalProvision"
      }
    },
    {
      "@id": "estleg:Cluster_VALISS_1",
      "@type": [
        "owl:NamedIndividual",
        "estleg:TopicCluster"
      ],
      "rdfs:label": "§1–3 ÜLDSÄTTED"
    },
    {
      "@id": "estleg:Cluster_VALISS_2",
      "@type": [
        "owl:NamedIndividual",
        "estleg:TopicCluster"
      ],
      "rdfs:label": "§4–11 VÄLISSUHTLEMISASUTUSED JA NENDE PÄDEVUS"
    },
    {
      "@id": "estleg:Cluster_VALISS_3",
      "@type": [
        "owl:NamedIndividual",
        "estleg:TopicCluster"
      ],
      "rdfs:label": "§12–28 VÄLISLEPING"
    },
    {
      "@id": "estleg:Cluster_VALISS_4",
      "@type": [
        "owl:NamedIndividual",
        "estleg:TopicCluster"
      ],
      "rdfs:label": "§29–32 AMETKONDLIK VÄLISLEPING"
    },
    {
      "@id": "estleg:Cluster_VALISS_5",
      "@type": [
        "owl:NamedIndividual",
        "estleg:TopicCluster"
      ],
      "rdfs:label": "§33–36 RAKENDUSSÄTTED"
    },
    {
      "@id": "estleg:VALISS_Par_1",
      "@type": [
        "owl:NamedIndividual",
        "estleg:LegalProvision_VALISS"
      ],
      "estleg:paragrahv": "§ 1.",
      "rdfs:label": "§ 1. Seaduse reguleerimisala",
      "estleg:sourceAct": "Välissuhtlemisseadus",
      "estleg:summary": "1 (1) Välissuhtlemisseadusega reguleeritakse Eesti Vabariigi välissuhtlemist, Eesti Vabariigi välissuhtlemisasutuste (edaspidi välissuhtlemisasutused) pädevust ja välislepingute riigisisest menetlust. Välissuhtlemisseadusega reguleeritakse Eesti Vabariigi välissuhtlemist, Eesti Vabariigi välissuhtlemisasutuste (edaspidi välissuhtlemisasutused) pädevust ja välislepingute riigisisest menetlust. 2 (2) Käesoleva seadusega ei reguleerita Eesti Vabariigi suhtlemist Euroopa Liiduga, välja arvatud juhul",
      "estleg:requestedCluster": "estleg:Cluster_VALISS_1"
    },
    {
      "@id": "estleg:VALISS_Par_2",
      "@type": [
        "owl:NamedIndividual",
        "estleg:LegalProvision_VALISS"
      ],
      "estleg:paragrahv": "§ 2.",
      "rdfs:label": "§ 2. Välissuhtlemise alused",
      "estleg:sourceAct": "Välissuhtlemisseadus",
      "estleg:summary": "Välissuhtlemisel juhindutakse: 1 1) käesolevast seadusest ja teistest Eesti Vabariigi õigusaktidest; 2 2) rahvusvahelise õiguse üldtunnustatud põhimõtetest ning rahvusvahelisest tavast ja praktikast; 3 3) Eesti Vabariigi rahvusvahelistest kohustustest. Välissuhtlemisel juhindutakse: käesolevast seadusest ja teistest Eesti Vabariigi õigusaktidest; rahvusvahelise õiguse üldtunnustatud põhimõtetest ning rahvusvahelisest tavast ja praktikast; Eesti Vabariigi rahvusvahelistest kohustustest.",
      "estleg:requestedCluster": "estleg:Cluster_VALISS_1"
    },
    {
      "@id": "estleg:VALISS_Par_3",
      "@type": [
        "owl:NamedIndividual",
        "estleg:LegalProvision_VALISS"
      ],
      "estleg:paragrahv": "§ 3.",
      "rdfs:label": "§ 3. Põhimõisted",
      "estleg:sourceAct": "Välissuhtlemisseadus",
      "estleg:summary": "Käesoleva seaduse tähenduses on: 1 1) välissuhtlemine – pädevate välissuhtlemisasutuste suhtlemine välisriikide ja rahvusvaheliste organisatsioonidega; 2 2) välisleping – Eesti Vabariigi ja välisriigi või rahvusvahelise organisatsiooni kahe- või mitmepoolne ühest või mitmest dokumendist koosnev kirjalik kokkulepe, mida reguleeritakse rahvusvahelise õigusega; 3 3) ametkondlik välisleping – Eesti Vabariigi riigiasutuse või omavalitsusüksuse ja välisriigi asutuse või rahvusvahelise organisatsiooni ",
      "estleg:requestedCluster": "estleg:Cluster_VALISS_1"
    },
    {
      "@id": "estleg:VALISS_Par_4",
      "@type": [
        "owl:NamedIndividual",
        "estleg:LegalProvision_VALISS"
      ],
      "estleg:paragrahv": "§ 4.",
      "rdfs:label": "§ 4. Välissuhtlemisasutused",
      "estleg:sourceAct": "Välissuhtlemisseadus",
      "estleg:summary": "1 (1) Välissuhtlemist teostavad: 1 1) Riigikogu; 2 2) Vabariigi President; 3 3) Vabariigi Valitsus; 4 4) Välisministeerium; 5 5) teised riigiasutused ja omavalitsusüksused vastavalt oma pädevusele. Välissuhtlemist teostavad: Riigikogu; Vabariigi President; Vabariigi Valitsus; Välisministeerium; teised riigiasutused ja omavalitsusüksused vastavalt oma pädevusele. 2 (2) Välissuhtlemisasutused teavitavad Välisministeeriumi oma välissuhtlemisalasest tegevusest. Välissuhtlemisasutused teavitavad Väli",
      "estleg:requestedCluster": "estleg:Cluster_VALISS_2",
      "estleg:competentAuthority": [
        {
          "@id": "estleg:Institution_vabariigivalitsus"
        },
        {
          "@id": "estleg:Institution_riigikogu"
        },
        {
          "@id": "estleg:Institution_vabariigipresident"
        },
        {
          "@id": "estleg:Institution_vlisministeerium"
        }
      ],
      "estleg:competenceType": "general"
    },
    {
      "@id": "estleg:VALISS_Par_5",
      "@type": [
        "owl:NamedIndividual",
        "estleg:LegalProvision_VALISS"
      ],
      "estleg:paragrahv": "§ 5.",
      "rdfs:label": "§ 5.",
      "estleg:sourceAct": "Välissuhtlemisseadus",
      "estleg:summary": "1 (1) Eesti Vabariigi välisesindus (edaspidi välisesindus) on välisriigis asuv Välisministeeriumi struktuuriüksus, kes teostab välissuhtlemist asukohariigis või rahvusvahelises organisatsioonis käesoleva seaduse, oma põhimääruse ja teiste Eesti Vabariigi õigusaktide alusel ning lähtub oma tegevuses rahvusvahelisest õigusest. Eesti Vabariigi välisesindus (edaspidi välisesindus) on välisriigis asuv Välisministeeriumi struktuuriüksus, kes teostab välissuhtlemist asukohariigis või rahvusvahelises or",
      "estleg:requestedCluster": "estleg:Cluster_VALISS_2"
    },
    {
      "@id": "estleg:VALISS_Par_6",
      "@type": [
        "owl:NamedIndividual",
        "estleg:LegalProvision_VALISS"
      ],
      "estleg:paragrahv": "§ 6.",
      "rdfs:label": "§ 6. Riigikogu pädevus",
      "estleg:sourceAct": "Välissuhtlemisseadus",
      "estleg:summary": "1 (1) Riigikogu: 1 1) võtab vastu välissuhtlemisalaseid seadusi ja otsuseid; 2 2) ratifitseerib välislepinguid ühinemise, heakskiitmise, ratifitseerimise või muu seaduse vastuvõtmisega ja denonsseerib ratifitseeritud välislepinguid denonsseerimise, lepingust taganemise, lepingu lõpetamise või muu seaduse vastuvõtmisega; 3 3) esineb välispoliitikaalaste avalduste, deklaratsioonide ja pöördumistega või ühineb nendega; 4 4) suhtleb teiste riikide parlamentide ja parlamentidevaheliste organisatsioon",
      "estleg:requestedCluster": "estleg:Cluster_VALISS_2",
      "estleg:competentAuthority": [
        {
          "@id": "estleg:Institution_riigikogu"
        }
      ],
      "estleg:competenceType": "general"
    },
    {
      "@id": "estleg:VALISS_Par_7",
      "@type": [
        "owl:NamedIndividual",
        "estleg:LegalProvision_VALISS"
      ],
      "estleg:paragrahv": "§ 7.",
      "rdfs:label": "§ 7. Vabariigi Presidendi pädevus",
      "estleg:sourceAct": "Välissuhtlemisseadus",
      "estleg:summary": "Vabariigi President: 1 1) esindab riigipeana Eesti Vabariiki välissuhtlemises; 2 2) nimetab ja kutsub tagasi Vabariigi Valitsuse ettepanekul Eesti Vabariigi erakorralised ja täievolilised suursaadikud ja saadikud, kirjutades alla nende voli- ja tagasikutsumiskirjadele; 3 3) võtab vastu Eesti Vabariiki akrediteeritud erakorraliste ja täievoliliste suursaadikute ja saadikute volikirju; 4 4) kuulutab välisriigi diplomaatilise esinduse juhi rahvusvahelise õiguse kohaselt persona non grata’ks; 5 5) k",
      "estleg:requestedCluster": "estleg:Cluster_VALISS_2",
      "estleg:competentAuthority": [
        {
          "@id": "estleg:Institution_vabariigivalitsus"
        },
        {
          "@id": "estleg:Institution_vabariigipresident"
        }
      ],
      "estleg:competenceType": "general"
    },
    {
      "@id": "estleg:VALISS_Par_8",
      "@type": [
        "owl:NamedIndividual",
        "estleg:LegalProvision_VALISS"
      ],
      "estleg:paragrahv": "§ 8.",
      "rdfs:label": "§ 8. Vabariigi Valitsuse pädevus",
      "estleg:sourceAct": "Välissuhtlemisseadus",
      "estleg:summary": "1 (1) Vabariigi Valitsus: 1 1) korraldab välissuhtlemist ning viib ellu Eesti Vabariigi välispoliitikat; 2 2) korraldab välissuhtlemisalaste seaduste ja Riigikogu otsuste täitmist; 3 3) esitab Riigikogule välissuhtlemisalaseid õigusaktide eelnõusid ning välislepinguid ja nende eelnõusid; 4 4) kiidab heaks ja esitab Riigikogule ettekande riigi välispoliitikast; 5 5) kiidab heaks ja esitab Riigikogule julgeolekupoliitika alused; 6 6) tunnustab teisi riike ja valitsusi ning sõlmib teiste riikidega ",
      "estleg:requestedCluster": "estleg:Cluster_VALISS_2",
      "estleg:competentAuthority": [
        {
          "@id": "estleg:Institution_vabariigivalitsus"
        },
        {
          "@id": "estleg:Institution_riigikogu"
        }
      ],
      "estleg:competenceType": "enforcement"
    },
    {
      "@id": "estleg:VALISS_Par_9",
      "@type": [
        "owl:NamedIndividual",
        "estleg:LegalProvision_VALISS"
      ],
      "estleg:paragrahv": "§ 9.",
      "rdfs:label": "§ 9. Välisministeeriumi pädevus",
      "estleg:sourceAct": "Välissuhtlemisseadus",
      "estleg:summary": "1 (1) Välispoliitika kavandamisel ja teostamisel Välisministeerium: 1 1) korraldab ja koordineerib välissuhtlemist; 2 2) koostab vähemalt üks kord aastas Vabariigi Valitsuse ettekande riigi välispoliitikast; 3 3) töötab välja koos asjaomaste ministeeriumidega julgeolekupoliitika alused; 4 4) töötab välja koos asjaomaste ministeeriumidega viisapoliitika ning viib seda vastavalt oma pädevusele ellu; 5 5) töötab välja koos asjaomaste ministeeriumidega välismajanduspoliitika, sealhulgas väliskauband",
      "estleg:requestedCluster": "estleg:Cluster_VALISS_2",
      "estleg:competentAuthority": [
        {
          "@id": "estleg:Institution_vabariigivalitsus"
        },
        {
          "@id": "estleg:Institution_vlisministeerium"
        }
      ],
      "estleg:competenceType": "enforcement"
    },
    {
      "@id": "estleg:VALISS_Par_10",
      "@type": [
        "owl:NamedIndividual",
        "estleg:LegalProvision_VALISS"
      ],
      "estleg:paragrahv": "§ 10.",
      "rdfs:label": "§ 10. Riigiasutuste ja omavalitsusüksuste pädevus",
      "estleg:sourceAct": "Välissuhtlemisseadus",
      "estleg:summary": "1 (1) Teised riigiasutused ja omavalitsusüksused teostavad välissuhtlemist vastavalt seaduse või muu õigusaktiga määratud pädevusele või antud volitustele ning Välisministeeriumi taotluse korral teavitavad Välisministeeriumi oma välissuhtlemisalasest tegevusest. Teised riigiasutused ja omavalitsusüksused teostavad välissuhtlemist vastavalt seaduse või muu õigusaktiga määratud pädevusele või antud volitustele ning Välisministeeriumi taotluse korral teavitavad Välisministeeriumi oma välissuhtlemis",
      "estleg:requestedCluster": "estleg:Cluster_VALISS_2"
    },
    {
      "@id": "estleg:VALISS_Par_11",
      "@type": [
        "owl:NamedIndividual",
        "estleg:LegalProvision_VALISS"
      ],
      "estleg:paragrahv": "§ 11.",
      "rdfs:label": "§ 11. Välisesinduse pädevus",
      "estleg:sourceAct": "Välissuhtlemisseadus",
      "estleg:summary": "1 (1) Diplomaatiline esindus: 1 1) esindab Eesti Vabariiki ning kaitseb Eesti Vabariigi huve ja õigusi asukohariigis või rahvusvahelises organisatsioonis; 2 2) arendab Eesti Vabariigi ja asukohariigi suhteid; 3 3) peab läbirääkimisi asukohariigi institutsioonide, rahvusvahelise organisatsiooni üksuste ja rahvusvahelises organisatsioonis esindatud riikide esindajatega; 4 4) kaitseb Eesti Vabariigi isikute huve ja õigusi asukohariigis või rahvusvahelise organisatsiooni töövaldkonda kuuluvates küsi",
      "estleg:requestedCluster": "estleg:Cluster_VALISS_2",
      "estleg:normativeType": [
        {
          "@id": "estleg:NormType_Obligation"
        }
      ]
    },
    {
      "@id": "estleg:VALISS_Par_12",
      "@type": [
        "owl:NamedIndividual",
        "estleg:LegalProvision_VALISS"
      ],
      "estleg:paragrahv": "§ 12.",
      "rdfs:label": "§ 12. Välislepingu sõlmimise algatamine",
      "estleg:sourceAct": "Välissuhtlemisseadus",
      "estleg:summary": "1 (1) Välislepingu sõlmimise algatamise õigus on Välisministeeriumil. Välislepingu sõlmimise algatamise õigus on Välisministeeriumil. 2 (2) Ministeeriumid ja Riigikantselei esitavad välislepingu sõlmimise algatamise ettepaneku Välisministeeriumile. Ministeeriumid ja Riigikantselei esitavad välislepingu sõlmimise algatamise ettepaneku Välisministeeriumile.",
      "estleg:requestedCluster": "estleg:Cluster_VALISS_3",
      "estleg:normativeType": [
        {
          "@id": "estleg:NormType_Right"
        }
      ]
    },
    {
      "@id": "estleg:VALISS_Par_13",
      "@type": [
        "owl:NamedIndividual",
        "estleg:LegalProvision_VALISS"
      ],
      "estleg:paragrahv": "§ 13.",
      "rdfs:label": "§ 13. Välislepingu sõlmimise ettevalmistamine",
      "estleg:sourceAct": "Välissuhtlemisseadus",
      "estleg:summary": "1 (1) Välislepingu sõlmimise ettevalmistamist juhib Välisministeerium või Välisministeeriumi nõusolekul muu ministeerium või Riigikantselei, kaasates Välisministeeriumi esindaja. Välislepingu sõlmimise ettevalmistamist juhib Välisministeerium või Välisministeeriumi nõusolekul muu ministeerium või Riigikantselei, kaasates Välisministeeriumi esindaja. 2 (2) Välislepingu sõlmimise ettevalmistamisse kaasatakse ministeeriumid ja muud valitsusasutused, kelle valitsemisala välislepingus käsitletakse. V",
      "estleg:requestedCluster": "estleg:Cluster_VALISS_3",
      "estleg:competentAuthority": [
        {
          "@id": "estleg:Institution_vlisministeerium"
        }
      ],
      "estleg:competenceType": "general"
    },
    {
      "@id": "estleg:VALISS_Par_14",
      "@type": [
        "owl:NamedIndividual",
        "estleg:LegalProvision_VALISS"
      ],
      "estleg:paragrahv": "§ 14.",
      "rdfs:label": "§ 14. Välislepingu materjalide esitamine Välisministeeriumile",
      "estleg:sourceAct": "Välissuhtlemisseadus",
      "estleg:summary": "1 (1) Välislepingu sõlmimise ettevalmistamist juhtinud ministeerium või Riigikantselei esitab Välisministeeriumile järgmised nõuetekohased materjalid Vabariigi Valitsusele esitamiseks: 1 1) välislepingu eelnõu tekst, vastuvõetud välislepingu korral välislepingu ametlik tekst, ja korrektne tõlge eesti keelde, kui välislepingu eelnõu või välislepingu autentne tekst on ainult võõrkeeltes; 2 2) asjaomaste ministeeriumide kooskõlastuskirjad; 3 3) riigisisese õigusakti eelnõu välislepingu kohta; 4 4) ",
      "estleg:requestedCluster": "estleg:Cluster_VALISS_3",
      "estleg:competentAuthority": [
        {
          "@id": "estleg:Institution_vabariigivalitsus"
        }
      ],
      "estleg:competenceType": "general"
    },
    {
      "@id": "estleg:VALISS_Par_15",
      "@type": [
        "owl:NamedIndividual",
        "estleg:LegalProvision_VALISS"
      ],
      "estleg:paragrahv": "§ 15.",
      "rdfs:label": "§ 15. Välisministeeriumi pädevus välislepingu materjalide läbivaatamisel",
      "estleg:sourceAct": "Välissuhtlemisseadus",
      "estleg:summary": "1 (1) Välisministeerium kontrollib talle esitatud §-s 14 nimetatud materjalide vastavust õigusaktidele. Välisministeerium kontrollib talle esitatud §-s 14 nimetatud materjalide vastavust õigusaktidele. 2 (2) Kui välislepingu materjalides on puudusi, määrab Välisministeerium puuduste kõrvaldamiseks mõistliku tähtaja. Kui välislepingu materjalides on puudusi, määrab Välisministeerium puuduste kõrvaldamiseks mõistliku tähtaja. 3 (3) Välisministeerium esitab nõuetekohased välislepingu materjalid Vab",
      "estleg:requestedCluster": "estleg:Cluster_VALISS_3",
      "estleg:competentAuthority": [
        {
          "@id": "estleg:Institution_vlisministeerium"
        }
      ],
      "estleg:competenceType": "enforcement"
    },
    {
      "@id": "estleg:VALISS_Par_16",
      "@type": [
        "owl:NamedIndividual",
        "estleg:LegalProvision_VALISS"
      ],
      "estleg:paragrahv": "§ 16.",
      "rdfs:label": "§ 16. Välislepingu heakskiitmine Vabariigi Valitsuses",
      "estleg:sourceAct": "Välissuhtlemisseadus",
      "estleg:summary": "Sõlmimiseks ettevalmistatud välislepingu kiidab heaks Vabariigi Valitsus. Sõlmimiseks ettevalmistatud välislepingu kiidab heaks Vabariigi Valitsus.",
      "estleg:requestedCluster": "estleg:Cluster_VALISS_3",
      "estleg:competentAuthority": [
        {
          "@id": "estleg:Institution_vabariigivalitsus"
        }
      ],
      "estleg:competenceType": "general"
    },
    {
      "@id": "estleg:VALISS_Par_17",
      "@type": [
        "owl:NamedIndividual",
        "estleg:LegalProvision_VALISS"
      ],
      "estleg:paragrahv": "§ 17.",
      "rdfs:label": "§ 17. Välislepingu allakirjutamise volitused",
      "estleg:sourceAct": "Välissuhtlemisseadus",
      "estleg:summary": "1 (1) Ametikoha järgi (ex officio) ja ilma volikirjata kirjutab Vabariigi Valitsuse heakskiidetud välislepingule Eesti Vabariigi nimel alla: 1 1) Vabariigi President, peaminister või välisminister või 2 2) diplomaatilise esinduse juht, kes on akrediteeritud riiki või rahvusvahelise organisatsiooni juurde, kellega leping sõlmitakse. Ametikoha järgi (ex officio) ja ilma volikirjata kirjutab Vabariigi Valitsuse heakskiidetud välislepingule Eesti Vabariigi nimel alla: Vabariigi President, peaministe",
      "estleg:requestedCluster": "estleg:Cluster_VALISS_3",
      "estleg:competentAuthority": [
        {
          "@id": "estleg:Institution_vabariigivalitsus"
        },
        {
          "@id": "estleg:Institution_vabariigipresident"
        },
        {
          "@id": "estleg:Institution_peaminister"
        },
        {
          "@id": "estleg:Institution_vlisminister"
        }
      ],
      "estleg:competenceType": "general"
    },
    {
      "@id": "estleg:VALISS_Par_18",
      "@type": [
        "owl:NamedIndividual",
        "estleg:LegalProvision_VALISS"
      ],
      "estleg:paragrahv": "§ 18.",
      "rdfs:label": "§ 18. Välislepingu teksti vastuvõtmise volitused",
      "estleg:sourceAct": "Välissuhtlemisseadus",
      "estleg:summary": "1 (1) Välislepingu teksti vastuvõtmisel rahvusvahelisel nõupidamisel, rahvusvahelises organisatsioonis või selle allasutuses esindab Eesti Vabariiki sellel nõupidamisel, selles organisatsioonis või allasutuses esindama volitatud isik. Välislepingu teksti vastuvõtmisel rahvusvahelisel nõupidamisel, rahvusvahelises organisatsioonis või selle allasutuses esindab Eesti Vabariiki sellel nõupidamisel, selles organisatsioonis või allasutuses esindama volitatud isik. 2 (2) Käesoleva paragrahvi lõikes 1 ",
      "estleg:requestedCluster": "estleg:Cluster_VALISS_3"
    },
    {
      "@id": "estleg:VALISS_Par_19",
      "@type": [
        "owl:NamedIndividual",
        "estleg:LegalProvision_VALISS"
      ],
      "estleg:paragrahv": "§ 19.",
      "rdfs:label": "§ 19. Välislepingu sõlmimine",
      "estleg:sourceAct": "Välissuhtlemisseadus",
      "estleg:summary": "Välislepingu sõlmimisega võtab Eesti Vabariik endale välislepingus ettenähtud kohustused. Välisleping sõlmitakse sellele alla kirjutades, lepingut ratifitseerides, heaks kiites, sellega ühinedes või muul lepingus ettenähtud viisil. Välislepingu sõlmimisega võtab Eesti Vabariik endale välislepingus ettenähtud kohustused. Välisleping sõlmitakse sellele alla kirjutades, lepingut ratifitseerides, heaks kiites, sellega ühinedes või muul lepingus ettenähtud viisil.",
      "estleg:requestedCluster": "estleg:Cluster_VALISS_3"
    },
    {
      "@id": "estleg:VALISS_Par_20",
      "@type": [
        "owl:NamedIndividual",
        "estleg:LegalProvision_VALISS"
      ],
      "estleg:paragrahv": "§ 20.",
      "rdfs:label": "§ 20. Välislepingu ratifitseerimine",
      "estleg:sourceAct": "Välissuhtlemisseadus",
      "estleg:summary": "Välisleping ratifitseeritakse Riigikogus, kui: 1 1) välislepinguga muudetakse riigipiire; 2 2) välislepingu rakendamiseks on tarvis võtta vastu, muuta või kehtetuks tunnistada Eesti Vabariigi seadusi; 3 3) välislepingu kohaselt ühineb Eesti Vabariik rahvusvahelise organisatsiooni või liiduga; 4 4) välislepinguga võtab Eesti Vabariik sõjalisi kohustusi; 5 5) välislepinguga võtab Eesti Vabariik avalik-õiguslikes suhetes varalisi kohustusi, mille täitmiseks ei ole riigieelarves vahendeid ette nähtu",
      "estleg:requestedCluster": "estleg:Cluster_VALISS_3",
      "estleg:competentAuthority": [
        {
          "@id": "estleg:Institution_riigikogu"
        }
      ],
      "estleg:competenceType": "general"
    },
    {
      "@id": "estleg:VALISS_Par_21",
      "@type": [
        "owl:NamedIndividual",
        "estleg:LegalProvision_VALISS"
      ],
      "estleg:paragrahv": "§ 21.",
      "rdfs:label": "§ 21. Välislepingu jõustamine",
      "estleg:sourceAct": "Välissuhtlemisseadus",
      "estleg:summary": "1 (1) Välislepingu jõustamisega avaldab Eesti Vabariik valmisolekut täita endale lepingu sõlmimisega võetud kohustusi. Välisleping jõustatakse allakirjutamisega, lepingukirjaga või muul lepingus ettenähtud viisil. Välislepingu jõustamisega avaldab Eesti Vabariik valmisolekut täita endale lepingu sõlmimisega võetud kohustusi. Välisleping jõustatakse allakirjutamisega, lepingukirjaga või muul lepingus ettenähtud viisil. 2 (2) Tulenevalt välislepingust võib lepingukiri olla: 1 1) ratifitseerimiskir",
      "estleg:requestedCluster": "estleg:Cluster_VALISS_3",
      "estleg:normativeType": [
        {
          "@id": "estleg:NormType_Right"
        }
      ]
    },
    {
      "@id": "estleg:VALISS_Par_22",
      "@type": [
        "owl:NamedIndividual",
        "estleg:LegalProvision_VALISS"
      ],
      "estleg:paragrahv": "§ 22.",
      "rdfs:label": "§ 22. Reservatsioonide ja deklaratsioonide tegemine, muutmine ja tagasivõtmine",
      "estleg:sourceAct": "Välissuhtlemisseadus",
      "estleg:summary": "1 (1) Reservatsioone võib välislepingu kohta teha välislepingut sõlmides välislepingu tingimuste kohaselt. Reservatsioone võib välislepingu kohta teha välislepingut sõlmides välislepingu tingimuste kohaselt. 2 (2) Deklaratsioone võib välislepingu kohta teha välislepingut sõlmides või välislepingut täites. Deklaratsioone võib välislepingu kohta teha välislepingut sõlmides või välislepingut täites. 3 (3) Välislepingu kohta tehtud reservatsioonide muutmise ja tagasivõtmise õigus on välislepingu sõl",
      "estleg:requestedCluster": "estleg:Cluster_VALISS_3",
      "estleg:normativeType": [
        {
          "@id": "estleg:NormType_Right"
        }
      ]
    },
    {
      "@id": "estleg:VALISS_Par_23",
      "@type": [
        "owl:NamedIndividual",
        "estleg:LegalProvision_VALISS"
      ],
      "estleg:paragrahv": "§ 23.",
      "rdfs:label": "§ 23. Välislepingu täitmise tagamine",
      "estleg:sourceAct": "Välissuhtlemisseadus",
      "estleg:summary": "1 (1) Välislepingu täitmise tagab Vabariigi Valitsus või selleks volitatud valitsusasutus. Välislepingu täitmise tagab Vabariigi Valitsus või selleks volitatud valitsusasutus. 2 (2) Vabariigi Valitsus võib välislepingut pärast selle heakskiitmist ja enne selle jõustumist ajutiselt kohaldada tingimusel, et sellega ei piirata isiku põhiõigusi ega -vabadusi ning välislepingu ajutine kohaldamine on ette nähtud välislepingus või Vabariigi Valitsuse õigusaktis. Vabariigi Valitsus võib välislepingut pä",
      "estleg:requestedCluster": "estleg:Cluster_VALISS_3",
      "estleg:normativeType": [
        {
          "@id": "estleg:NormType_Right"
        }
      ],
      "estleg:competentAuthority": [
        {
          "@id": "estleg:Institution_vabariigivalitsus"
        }
      ],
      "estleg:competenceType": "general"
    },
    {
      "@id": "estleg:VALISS_Par_24",
      "@type": [
        "owl:NamedIndividual",
        "estleg:LegalProvision_VALISS"
      ],
      "estleg:paragrahv": "§ 24.",
      "rdfs:label": "§ 24. Välislepingu ja riigisisese õigusakti vastuolu",
      "estleg:sourceAct": "Välissuhtlemisseadus",
      "estleg:summary": "1 (1) Kui Riigikohus on tunnistanud, et välisleping või selle osa on põhiseadusega vastuolus, teeb välislepingust taganemise, selle denonsseerimise või muutmise menetluse algatamise ettepaneku: 1 1) Vabariigi Valitsus Riigikogule, kui Riigikogu on välislepingu ratifitseerinud; 2 2) Välisministeerium Vabariigi Valitsusele, kui välislepingu on sõlminud Vabariigi Valitsus. Kui Riigikohus on tunnistanud, et välisleping või selle osa on põhiseadusega vastuolus, teeb välislepingust taganemise, selle d",
      "estleg:requestedCluster": "estleg:Cluster_VALISS_3",
      "estleg:competentAuthority": [
        {
          "@id": "estleg:Institution_vabariigivalitsus"
        },
        {
          "@id": "estleg:Institution_riigikogu"
        },
        {
          "@id": "estleg:Institution_riigikohus"
        },
        {
          "@id": "estleg:Institution_vlisministeerium"
        }
      ],
      "estleg:competenceType": "general"
    },
    {
      "@id": "estleg:VALISS_Par_25",
      "@type": [
        "owl:NamedIndividual",
        "estleg:LegalProvision_VALISS"
      ],
      "estleg:paragrahv": "§ 25.",
      "rdfs:label": "§ 25. Välislepingu muutmine",
      "estleg:sourceAct": "Välissuhtlemisseadus",
      "estleg:summary": "1 (1) Välislepingut muudetakse välislepingu sõlmimisega samas korras, kui välislepingus ei ole ette nähtud teisiti. Välislepingut muudetakse välislepingu sõlmimisega samas korras, kui välislepingus ei ole ette nähtud teisiti. 2 (2) Vabariigi Valitsus võib anda nõusoleku muuta Riigikogus ratifitseeritud välislepingut, kui üheaegselt esinevad järgmised tingimused: 1 1) muudatus ei ole sisulist laadi; 2 2) muutmiseks on vaja Eesti Vabariigi kinnitust rahvusvahelise organisatsiooni muudatusettepanek",
      "estleg:requestedCluster": "estleg:Cluster_VALISS_3",
      "estleg:normativeType": [
        {
          "@id": "estleg:NormType_Right"
        }
      ],
      "estleg:competentAuthority": [
        {
          "@id": "estleg:Institution_vabariigivalitsus"
        },
        {
          "@id": "estleg:Institution_riigikogu"
        }
      ],
      "estleg:competenceType": "general"
    },
    {
      "@id": "estleg:VALISS_Par_26",
      "@type": [
        "owl:NamedIndividual",
        "estleg:LegalProvision_VALISS"
      ],
      "estleg:paragrahv": "§ 26.",
      "rdfs:label": "§ 26. Välislepingu lõppemine",
      "estleg:sourceAct": "Välissuhtlemisseadus",
      "estleg:summary": "1 (1) Välisleping lõpeb selles ettenähtud või muul rahvusvahelise õigusega sätestatud viisil. Välisleping lõpeb selles ettenähtud või muul rahvusvahelise õigusega sätestatud viisil. 2 (2) Kui teine lepingupool denonsseerib ratifitseeritud välislepingu, teeb Vabariigi Valitsus Riigikogule ettepaneku tunnistada kehtetuks välislepinguga ühinemise, välislepingu heakskiitmise ja ratifitseerimise või muu seadus. Kui teine lepingupool denonsseerib ratifitseeritud välislepingu, teeb Vabariigi Valitsus R",
      "estleg:requestedCluster": "estleg:Cluster_VALISS_3",
      "estleg:competentAuthority": [
        {
          "@id": "estleg:Institution_vabariigivalitsus"
        },
        {
          "@id": "estleg:Institution_riigikogu"
        }
      ],
      "estleg:competenceType": "general"
    },
    {
      "@id": "estleg:VALISS_Par_27",
      "@type": [
        "owl:NamedIndividual",
        "estleg:LegalProvision_VALISS"
      ],
      "estleg:paragrahv": "§ 27.",
      "rdfs:label": "§ 27. Välislepingu denonsseerimine, lõpetamine ja sellest taganemine",
      "estleg:sourceAct": "Välissuhtlemisseadus",
      "estleg:summary": "1 (1) Ratifitseeritud välislepingu denonsseerimise otsustab Riigikogu. Ratifitseeritud välislepingu denonsseerimise otsustab Riigikogu. 2 (2) Käesoleva paragrahvi lõikes 1 nimetamata välislepingu lõpetamise või sellest taganemise otsustab Vabariigi Valitsus. Käesoleva paragrahvi lõikes 1 nimetamata välislepingu lõpetamise või sellest taganemise otsustab Vabariigi Valitsus. 3 (3) Välislepingu denonsseerimisest, lõpetamisest või sellest taganemisest teatab teisele lepingupoolele või hoiulevõtjale ",
      "estleg:requestedCluster": "estleg:Cluster_VALISS_3",
      "estleg:competentAuthority": [
        {
          "@id": "estleg:Institution_vabariigivalitsus"
        },
        {
          "@id": "estleg:Institution_riigikogu"
        }
      ],
      "estleg:competenceType": "general"
    },
    {
      "@id": "estleg:VALISS_Par_28",
      "@type": [
        "owl:NamedIndividual",
        "estleg:LegalProvision_VALISS"
      ],
      "estleg:paragrahv": "§ 28.",
      "rdfs:label": "§ 28. Välislepingu hoidmine ja avaldamine",
      "estleg:sourceAct": "Välissuhtlemisseadus",
      "estleg:summary": "1 (1) Kahe- ja kolmepoolse välislepingu originaali ning muud välislepingu ametlikku teksti hoitakse Välisministeeriumis. Kahe- ja kolmepoolse välislepingu originaali ning muud välislepingu ametlikku teksti hoitakse Välisministeeriumis. 2 (2) Välisleping avaldatakse Riigi Teatajas. Välisleping avaldatakse Riigi Teatajas. 3 (3) Riigi Teatajas ei avaldata välislepinguid, mis avaldatakse Euroopa Liidu Teatajas. Riigi Teatajas ei avaldata välislepinguid, mis avaldatakse Euroopa Liidu Teatajas.",
      "estleg:requestedCluster": "estleg:Cluster_VALISS_3"
    },
    {
      "@id": "estleg:VALISS_Par_29",
      "@type": [
        "owl:NamedIndividual",
        "estleg:LegalProvision_VALISS"
      ],
      "estleg:paragrahv": "§ 29.",
      "rdfs:label": "§ 29. Ametkondliku välislepingu sõlmimine",
      "estleg:sourceAct": "Välissuhtlemisseadus",
      "estleg:summary": "Riigiasutused ja omavalitsusüksused võivad vastavalt oma pädevusele iseseisvalt ette valmistada ja sõlmida ametkondlikke välislepinguid. Riigiasutused ja omavalitsusüksused võivad vastavalt oma pädevusele iseseisvalt ette valmistada ja sõlmida ametkondlikke välislepinguid.",
      "estleg:requestedCluster": "estleg:Cluster_VALISS_4"
    },
    {
      "@id": "estleg:VALISS_Par_30",
      "@type": [
        "owl:NamedIndividual",
        "estleg:LegalProvision_VALISS"
      ],
      "estleg:paragrahv": "§ 30.",
      "rdfs:label": "§ 30. Ametkondliku välislepingu avaldamine",
      "estleg:sourceAct": "Välissuhtlemisseadus",
      "estleg:summary": "Ametkondlik välisleping avaldatakse asjaomase riigiasutuse või omavalitsusüksuse veebilehel või ametlikus väljaandes, kui ametkondlikus välislepingus ei ole sätestatud teisiti. Ametkondlik välisleping avaldatakse asjaomase riigiasutuse või omavalitsusüksuse veebilehel või ametlikus väljaandes, kui ametkondlikus välislepingus ei ole sätestatud teisiti.",
      "estleg:requestedCluster": "estleg:Cluster_VALISS_4"
    },
    {
      "@id": "estleg:VALISS_Par_31",
      "@type": [
        "owl:NamedIndividual",
        "estleg:LegalProvision_VALISS"
      ],
      "estleg:paragrahv": "§ 31.",
      "rdfs:label": "§ 31. Ametkondlikust välislepingust teatamine",
      "estleg:sourceAct": "Välissuhtlemisseadus",
      "estleg:summary": "1 (1) Valitsusasutus teatab sõlmitud ametkondlikust välislepingust Välisministeeriumile. Valitsusasutus teatab sõlmitud ametkondlikust välislepingust Välisministeeriumile. 2 (2) Välisminister kehtestab määrusega ./dyn=13312087&id=12754159 valitsusasutuse ametkondlikust välislepingust teatamise korra. valitsusasutuse ametkondlikust välislepingust teatamise korra.",
      "estleg:requestedCluster": "estleg:Cluster_VALISS_4",
      "estleg:competentAuthority": [
        {
          "@id": "estleg:Institution_vlisminister"
        }
      ],
      "estleg:competenceType": "regulation"
    },
    {
      "@id": "estleg:VALISS_Par_32",
      "@type": [
        "owl:NamedIndividual",
        "estleg:LegalProvision_VALISS"
      ],
      "estleg:paragrahv": "§ 32.",
      "rdfs:label": "§ 32. Ametkondliku välislepingu muutmine, peatamine ja lõpetamine",
      "estleg:sourceAct": "Välissuhtlemisseadus",
      "estleg:summary": "Ametkondliku välislepingu muutmise, peatamise või lõpetamise otsustab asjaomane riigiasutus või omavalitsusüksus rahvusvahelise õiguse ja ametkondliku välislepingu kohaselt. Ametkondliku välislepingu muutmise, peatamise või lõpetamise otsustab asjaomane riigiasutus või omavalitsusüksus rahvusvahelise õiguse ja ametkondliku välislepingu kohaselt.",
      "estleg:requestedCluster": "estleg:Cluster_VALISS_4"
    },
    {
      "@id": "estleg:VALISS_Par_33",
      "@type": [
        "owl:NamedIndividual",
        "estleg:LegalProvision_VALISS"
      ],
      "estleg:paragrahv": "§ 33.",
      "rdfs:label": "§ 33.",
      "estleg:sourceAct": "Välissuhtlemisseadus",
      "estleg:requestedCluster": "estleg:Cluster_VALISS_5"
    },
    {
      "@id": "estleg:VALISS_Par_34",
      "@type": [
        "owl:NamedIndividual",
        "estleg:LegalProvision_VALISS"
      ],
      "estleg:paragrahv": "§ 35.",
      "rdfs:label": "§ 35.",
      "estleg:sourceAct": "Välissuhtlemisseadus",
      "estleg:summary": "[Käesolevast tekstist välja jäetud.]",
      "estleg:requestedCluster": "estleg:Cluster_VALISS_5"
    },
    {
      "@id": "estleg:VALISS_Par_36",
      "@type": [
        "owl:NamedIndividual",
        "estleg:LegalProvision_VALISS"
      ],
      "estleg:paragrahv": "§ 36.",
      "rdfs:label": "§ 36. Seaduse jõustumine",
      "estleg:sourceAct": "Välissuhtlemisseadus",
      "estleg:summary": "Käesolev seadus jõustub 2007. aasta 1. jaanuaril. Käesolev seadus jõustub 2007. aasta 1. jaanuaril.",
      "estleg:requestedCluster": "estleg:Cluster_VALISS_5"
    }
  ]
}
